Utils/CPMetrics.py
Utils/CertTools.py
Utils/EmailAlert.py
Utils/ExtendedUnitTestCase.py
Utils/FileTools.py
Utils/IteratorTools.py
Utils/MathUtils.py
Utils/MemoryCache.py
Utils/Patterns.py
Utils/Pipeline.py
Utils/PortForward.py
Utils/ProcessStats.py
Utils/PythonVersion.py
Utils/Signals.py
Utils/TemporaryEnvironment.py
Utils/Throttled.py
Utils/Timers.py
Utils/Timestamps.py
Utils/TokenManager.py
Utils/Tracing.py
Utils/TwPrint.py
Utils/Utilities.py
Utils/__init__.py
WMCore/Configuration.py
WMCore/DAOFactory.py
WMCore/Lexicon.py
WMCore/WMBase.py
WMCore/WMConnectionBase.py
WMCore/WMException.py
WMCore/WMExceptions.py
WMCore/WMFactory.py
WMCore/WMInit.py
WMCore/WMLogging.py
WMCore/__init__.py
WMCore/Algorithms/Alarm.py
WMCore/Algorithms/MathAlgos.py
WMCore/Algorithms/MiscAlgos.py
WMCore/Algorithms/ParseXMLFile.py
WMCore/Algorithms/Permissions.py
WMCore/Algorithms/Singleton.py
WMCore/Algorithms/SubprocessAlgos.py
WMCore/Algorithms/__init__.py
WMCore/Cache/GenericDataCache.py
WMCore/Cache/WMConfigCache.py
WMCore/Cache/__init__.py
WMCore/DataStructs/File.py
WMCore/DataStructs/Fileset.py
WMCore/DataStructs/Job.py
WMCore/DataStructs/JobGroup.py
WMCore/DataStructs/JobPackage.py
WMCore/DataStructs/LumiList.py
WMCore/DataStructs/Mask.py
WMCore/DataStructs/Pickleable.py
WMCore/DataStructs/Run.py
WMCore/DataStructs/Subscription.py
WMCore/DataStructs/WMObject.py
WMCore/DataStructs/WorkUnit.py
WMCore/DataStructs/Workflow.py
WMCore/DataStructs/__init__.py
WMCore/DataStructs/MathStructs/ContinuousSummaryHistogram.py
WMCore/DataStructs/MathStructs/DiscreteSummaryHistogram.py
WMCore/DataStructs/MathStructs/SummaryHistogram.py
WMCore/DataStructs/MathStructs/__init__.py
WMCore/Database/CMSCouch.py
WMCore/Database/ConfigDBMap.py
WMCore/Database/CouchUtils.py
WMCore/Database/DBCore.py
WMCore/Database/DBCreator.py
WMCore/Database/DBExceptionHandler.py
WMCore/Database/DBFactory.py
WMCore/Database/DBFormatter.py
WMCore/Database/Dialects.py
WMCore/Database/ExecuteDAO.py
reqmgr2ms_output-2.3.10rc10.dist-info/LICENSE
reqmgr2ms_output-2.3.10rc10.dist-info/METADATA
reqmgr2ms_output-2.3.10rc10.dist-info/NOTICE
reqmgr2ms_output-2.3.10rc10.dist-info/WHEEL
reqmgr2ms_output-2.3.10rc10.dist-info/top_level.txt
reqmgr2ms_output-2.3.10rc10.dist-info/RECORD
